odoo8_addon_l10n_it_ricevute_bancarie-8.0.1.3.2-nspkg.pth
odoo_addons/l10n_it_ricevute_bancarie/README.rst
odoo_addons/l10n_it_ricevute_bancarie/__init__.py
odoo_addons/l10n_it_ricevute_bancarie/__openerp__.py
odoo_addons/l10n_it_ricevute_bancarie/report.xml
odoo_addons/l10n_it_ricevute_bancarie/riba_sequence.xml
odoo_addons/l10n_it_ricevute_bancarie/riba_workflow.xml
odoo_addons/l10n_it_ricevute_bancarie/demo/riba_demo.xml
odoo_addons/l10n_it_ricevute_bancarie/i18n/es.po
odoo_addons/l10n_it_ricevute_bancarie/i18n/it.po
odoo_addons/l10n_it_ricevute_bancarie/i18n/l10n_it_ricevute_bancarie.pot
odoo_addons/l10n_it_ricevute_bancarie/i18n/sl.po
odoo_addons/l10n_it_ricevute_bancarie/models/__init__.py
odoo_addons/l10n_it_ricevute_bancarie/models/account_config.py
odoo_addons/l10n_it_ricevute_bancarie/models/riba.py
odoo_addons/l10n_it_ricevute_bancarie/models/riba_config.py
odoo_addons/l10n_it_ricevute_bancarie/models/account/__init__.py
odoo_addons/l10n_it_ricevute_bancarie/models/account/account.py
odoo_addons/l10n_it_ricevute_bancarie/models/partner/__init__.py
odoo_addons/l10n_it_ricevute_bancarie/models/partner/partner.py
odoo_addons/l10n_it_ricevute_bancarie/report/__init__.py
odoo_addons/l10n_it_ricevute_bancarie/report/distinta_qweb.py
odoo_addons/l10n_it_ricevute_bancarie/security/ir.model.access.csv
odoo_addons/l10n_it_ricevute_bancarie/static/description/icon.png
odoo_addons/l10n_it_ricevute_bancarie/test/issue_riba.yml
odoo_addons/l10n_it_ricevute_bancarie/test/riba_invoice.yml
odoo_addons/l10n_it_ricevute_bancarie/test/unsolved_riba.yml
odoo_addons/l10n_it_ricevute_bancarie/tests/__init__.py
odoo_addons/l10n_it_ricevute_bancarie/tests/test_invoice_due_cost.py
odoo_addons/l10n_it_ricevute_bancarie/views/account_config_view.xml
odoo_addons/l10n_it_ricevute_bancarie/views/account_view.xml
odoo_addons/l10n_it_ricevute_bancarie/views/configuration_view.xml
odoo_addons/l10n_it_ricevute_bancarie/views/distinta_report.xml
odoo8_addon_l10n_it_ricevute_bancarie-8.0.1.3.2.dist-info/METADATA
odoo8_addon_l10n_it_ricevute_bancarie-8.0.1.3.2.dist-info/WHEEL
odoo8_addon_l10n_it_ricevute_bancarie-8.0.1.3.2.dist-info/namespace_packages.txt
odoo8_addon_l10n_it_ricevute_bancarie-8.0.1.3.2.dist-info/top_level.txt
odoo8_addon_l10n_it_ricevute_bancarie-8.0.1.3.2.dist-info/RECORD
