Metadata-Version: 2.1
Name: odoo8-addon-l10n-it-ricevute-bancarie
Version: 8.0.1.3.2
Summary: Ricevute Bancarie
Home-page: http://www.odoo-italia.org
Author: Odoo Community Association (OCA)
Author-email: support@odoo-community.org
License: AGPL-3
Platform: UNKNOWN
Classifier: Programming Language :: Python
Classifier: Framework :: Odoo
Classifier: License :: OSI Approved :: GNU Affero General Public License v3
Requires-Python: ~=2.7
Requires-Dist: odoo8-addon-account-due-list
Requires-Dist: odoo8-addon-l10n-it-abicab
Requires-Dist: odoo8-addon-l10n-it-fiscalcode
Requires-Dist: odoo (<9.0a,>=8.0a)
